azure_data_factory_generator/__init__.py
azure_data_factory_generator/__main__.py
azure_data_factory_generator/base.py
azure_data_factory_generator/defaults.py
azure_data_factory_generator/initialise.py
azure_data_factory_generator/schedule.py
azure_data_factory_generator/sftp.py
azure_data_factory_generator/activities/__init__.py
azure_data_factory_generator/activities/data_lake.py
azure_data_factory_generator/activities/generic.py
azure_data_factory_generator/templates/__init__.py
azure_data_factory_generator/templates/dataset/__init__.py
azure_data_factory_generator/templates/dataset/config_table.py
azure_data_factory_generator/templates/dataset/data_lake.py
azure_data_factory_generator/templates/dataset/ftp.py
azure_data_factory_generator/templates/dataset/sftp.py
azure_data_factory_generator/templates/linked_service/__init__.py
azure_data_factory_generator/templates/linked_service/config_table_storage.py
azure_data_factory_generator/templates/linked_service/data_lake.py
azure_data_factory_generator/templates/linked_service/ftp.py
azure_data_factory_generator/templates/linked_service/sftp.py
azure_data_factory_generator-0.1.4.dist-info/METADATA
azure_data_factory_generator-0.1.4.dist-info/WHEEL
azure_data_factory_generator-0.1.4.dist-info/dependency_links.txt
azure_data_factory_generator-0.1.4.dist-info/top_level.txt
azure_data_factory_generator-0.1.4.dist-info/RECORD
