Metadata-Version: 2.1
Name: azure-data-factory-generator
Version: 0.1.4
Summary: Generate Azure Data Factory objects from configuration
Home-page: https://github.com/ingenii-solutions/azure-data-factory-generator
Author: Greg Atkins
Author-email: greg@ingenii.dev
License: UNKNOWN
Platform: UNKNOWN
Classifier: Programming Language :: Python :: 3
Classifier: License :: OSI Approved :: Mozilla Public License 2.0 (MPL 2.0)
Classifier: Operating System :: OS Independent
Requires-Dist: deepdiff (==5.5.0)
